llm_edit.py
llm_edit-0.1.0.dist-info/METADATA
llm_edit-0.1.0.dist-info/WHEEL
llm_edit-0.1.0.dist-info/entry_points.txt
llm_edit-0.1.0.dist-info/licenses/LICENSE
llm_edit-0.1.0.dist-info/RECORD
