Metadata-Version: 2.4
Name: llm-edit
Version: 0.1.0
Summary: Add your description here
Project-URL: Homepage, https://github.com/ajac-zero/llm-dev
Author-email: ajac-zero <ajcardoza2000@gmail.com>
License: Apache-2.0
License-File: LICENSE
Classifier: License :: OSI Approved :: Apache Software License
Requires-Python: <3.14,>=3.9
Requires-Dist: llm
